README.md
setup.py
soundify/__init__.py
soundify/__main__.py
soundify/config.py
soundify/soundify.py
soundify.egg-info/PKG-INFO
soundify.egg-info/SOURCES.txt
soundify.egg-info/dependency_links.txt
soundify.egg-info/entry_points.txt
soundify.egg-info/requires.txt
soundify.egg-info/top_level.txt