Metadata-Version: 1.1
Name: soundify
Version: 0.3
Summary: soundify exitcodes
Home-page: https://github.com/amiremohamadi/Soundify
Author: amiremohamadi
Author-email: UNKNOWN
License: GPL V2.0
Keywords: sound playsound music wave wav mp3 media song play audio
Platform: UNKNOWN
Classifier: Programming Language :: Python :: 2
Classifier: Programming Language :: Python :: 2.3
Classifier: Programming Language :: Python :: 2.4
Classifier: Programming Language :: Python :: 2.5
Classifier: Programming Language :: Python :: 2.6
Classifier: Programming Language :: Python :: 2.7
Classifier: Programming Language :: Python :: 3
Classifier: Programming Language :: Python :: 3.1
Classifier: Programming Language :: Python :: 3.2
Classifier: Programming Language :: Python :: 3.3
Classifier: Programming Language :: Python :: 3.4
Classifier: Programming Language :: Python :: 3.5
Classifier: Topic :: Multimedia :: Sound/Audio :: MIDI
Classifier: Topic :: Multimedia :: Sound/Audio :: Players
Classifier: Topic :: Multimedia :: Sound/Audio :: Players :: MP3
